rupantar/__init__.py
rupantar/sohoj/__init__.py
rupantar/sohoj/builder.py
rupantar/sohoj/configger.py
rupantar/sohoj/creator.py
rupantar/sohoj/logger.py
rupantar/sohoj/server.py
rupantar/sohoj/server_watcher.py
rupantar/sohoj/utils.py
rupantar/start.py
rupantar-0.9.4.dist-info/entry_points.txt
rupantar-0.9.4.dist-info/LICENSE
rupantar-0.9.4.dist-info/METADATA
rupantar-0.9.4.dist-info/WHEEL
rupantar-0.9.4.dist-info/RECORD
