Metadata-Version: 2.1
Name: rupantar
Version: 0.9.4
Summary: Simple hackable static website generator with a focus on minimalism
Home-page: https://github.com/bhodrolok/rupantar
License: MIT
Author: bhodrolok
Author-email: korbolorbo1214@proton.me
Requires-Python: >=3.10,<4.0
Classifier: Development Status :: 3 - Alpha
Classifier: Environment :: Console
Classifier: Intended Audience :: Developers
Classifier: License :: OSI Approved :: MIT License
Classifier: Operating System :: MacOS :: MacOS X
Classifier: Operating System :: Microsoft :: Windows
Classifier: Operating System :: POSIX :: Linux
Classifier: Operating System :: Unix
Classifier: Programming Language :: Python :: 3
Classifier: Programming Language :: Python :: 3.10
Classifier: Programming Language :: Python :: 3.11
Classifier: Programming Language :: Python :: 3.12
Classifier: Topic :: Internet
Classifier: Topic :: Terminals
Requires-Dist: jinja2 (>=3.1.2,<4.0.0)
Requires-Dist: markdown2 (>=2.4.10,<3.0.0)
Requires-Dist: pyyaml (>=6.0.1,<7.0.0) ; python_version >= "3.6" and python_version < "4.0"
Requires-Dist: tomli (>=2.0.1,<3.0.0) ; python_version < "3.11"
Requires-Dist: watchfiles (>=0.21.0,<0.22.0)
Requires-Dist: xdg-base-dirs (>=6.0.1,<7.0.0)
Project-URL: Bug Tracker, https://github.com/bhodrolok/rupantar/issues
Project-URL: Repository, https://github.com/bhodrolok/rupantar
